README.md
beancount_share/__init__.py
beancount_share/share.py
beancount_share/utils.py
beancount_share-0.1.11.dist-info/LICENSE
beancount_share-0.1.11.dist-info/METADATA
beancount_share-0.1.11.dist-info/WHEEL
beancount_share-0.1.11.dist-info/top_level.txt
beancount_share-0.1.11.dist-info/RECORD
