Metadata-Version: 2.1
Name: beancount_share
Version: 0.1.11
Summary: Plugin for Beancount to share expenses.
Home-page: https://github.com/Akuukis/beancount_share
Download-URL: https://pypi.python.org/pypi/beancount_share
Author: Akuukis
Author-email: akuukis@kalvis.lv
License: GNU AGPLv3
License-File: LICENSE
Requires-Dist: beancount>=2.0
Requires-Dist: beancount_plugin_utils>=0.0.4
